fava_envelope-0.5.9.dist-info/METADATA
fava_envelope-0.5.9.dist-info/WHEEL
fava_envelope-0.5.9.dist-info/licenses/LICENSE
fava_envelope/__init__.py
fava_envelope/modules/__init__.py
fava_envelope/modules/beancount_envelope.py
fava_envelope/modules/main.py
fava_envelope/templates/EnvelopeBudget.html
fava_envelope/templates/__init__.py
fava_envelope/templates/_budget_table.html
fava_envelope-0.5.9.dist-info/RECORD
