Metadata-Version: 2.1
Name: fava-envelope
Version: 0.5.9
Keywords: fava,budget,envelope
Home-page: https://github.com/polarmutex/fava-envelope
Author: Brian Ryall
Author-Email: Unknown <me@brianryall.xyz>
License: MIT
Classifier: Development Status :: 4 - Beta
Classifier: Programming Language :: Python :: 3
Classifier: Programming Language :: Python :: 3 :: Only
Classifier: Programming Language :: Python :: 3.7
Classifier: Programming Language :: Python :: 3.8
Classifier: Programming Language :: Python :: 3.9
Project-URL: Homepage, https://github.com/polarmutex/fava-envelope
Project-URL: Documentation, https://github.com/polarmutex/fava-envelope
Project-URL: Repository, https://github.com/polarmutex/fava-envelope
Project-URL: Changelog, https://github.com/polarmutex/fava-envelope/master/CHANGELOG.md
Requires-Python: >=3.8
Requires-Dist: fava>=1.26
Requires-Dist: pandas>=2.0.3
